{
  "municipality": "Manaus",
  "municipalityIbge": "1302603",
  "state": "AM",
  "lastUpdated": "2026-02-07",
  "benefits": [
    {
      "id": "am-manaus-passa-facil-social",
      "name": "Passa Fácil Social",
      "shortDescription": "Cartão de transporte com tarifa reduzida para pessoas de baixa renda",
      "scope": "municipal",
      "state": "AM",
      "municipalityIbge": "1302603",
      "estimatedValue": {
        "type": "monthly",
        "min": 0,
        "max": 0,
        "description": "Tarifa reduzida de R$ 4,50"
      },
      "eligibilityRules": [
        {
          "field": "municipioIbge",
          "operator": "eq",
          "value": "1302603",
          "description": "Morar em Manaus"
        },
        {
          "field": "cadastradoCadunico",
          "operator": "eq",
          "value": true,
          "description": "Estar no CadÚnico"
        },
        {
          "field": "rendaPerCapita",
          "operator": "lte",
          "value": 810.5,
          "description": "Renda por pessoa até meio salário mínimo"
        }
      ],
      "whereToApply": "SMTU ou postos de atendimento",
      "documentsRequired": [
        "CPF",
        "RG",
        "NIS",
        "Comprovante de residência",
        "Foto 3x4"
      ],
      "howToApply": [
        "Procure a SMTU",
        "Apresente documentos",
        "Retire o cartão"
      ],
      "sourceUrl": "https://www.manaus.am.gov.br",
      "lastUpdated": "2026-02-07",
      "status": "active",
      "icon": "🚌",
      "category": "Transporte",
      "verified": true
    },
    {
      "id": "am-manaus-passe-livre-estudantil",
      "name": "Passe Livre Estudantil Manaus",
      "shortDescription": "Transporte gratuito para estudantes da rede pública",
      "scope": "municipal",
      "state": "AM",
      "municipalityIbge": "1302603",
      "estimatedValue": {
        "type": "monthly",
        "min": 0,
        "max": 0,
        "description": "Gratuidade total no transporte"
      },
      "eligibilityRules": [
        {
          "field": "municipioIbge",
          "operator": "eq",
          "value": "1302603",
          "description": "Morar em Manaus"
        },
        {
          "field": "estudante",
          "operator": "eq",
          "value": true,
          "description": "Ser estudante"
        },
        {
          "field": "redePublica",
          "operator": "eq",
          "value": true,
          "description": "Estudar em escola pública"
        }
      ],
      "whereToApply": "Escola ou SMTU",
      "documentsRequired": [
        "RG",
        "Declaração escolar",
        "Foto 3x4"
      ],
      "howToApply": [
        "Solicite na escola",
        "Aguarde aprovação",
        "Retire o cartão"
      ],
      "sourceUrl": "https://www.manaus.am.gov.br",
      "lastUpdated": "2026-02-07",
      "status": "active",
      "icon": "🎒",
      "category": "Transporte",
      "verified": true
    },
    {
      "id": "am-manaus-bolsa-universidade",
      "name": "Bolsa Universidade",
      "shortDescription": "Bolsa de estudos para universitários de baixa renda",
      "scope": "municipal",
      "state": "AM",
      "municipalityIbge": "1302603",
      "estimatedValue": {
        "type": "monthly",
        "min": 0,
        "max": 0,
        "description": "Bolsa integral ou parcial"
      },
      "eligibilityRules": [
        {
          "field": "municipioIbge",
          "operator": "eq",
          "value": "1302603",
          "description": "Morar em Manaus"
        },
        {
          "field": "estudante",
          "operator": "eq",
          "value": true,
          "description": "Ser estudante universitário"
        },
        {
          "field": "rendaPerCapita",
          "operator": "lte",
          "value": 1621,
          "description": "Renda por pessoa até 1 salário mínimo"
        }
      ],
      "whereToApply": "Secretaria Municipal de Educação",
      "documentsRequired": [
        "CPF",
        "RG",
        "Comprovante de matrícula",
        "Comprovante de renda"
      ],
      "howToApply": [
        "Aguarde edital",
        "Faça inscrição online",
        "Apresente documentos"
      ],
      "sourceUrl": "https://www.manaus.am.gov.br",
      "lastUpdated": "2026-02-07",
      "status": "active",
      "icon": "🎓",
      "category": "Educação",
      "verified": true
    },
    {
      "id": "am-manaus-restaurante-popular",
      "name": "Prato Cheio",
      "shortDescription": "Refeições a R$ 1 nas 18 unidades do Prato Cheio em Manaus. Programa do Governo do Estado do Amazonas",
      "scope": "municipal",
      "state": "AM",
      "municipalityIbge": "1302603",
      "estimatedValue": {
        "type": "monthly",
        "min": 0,
        "max": 0,
        "description": "Almoço R$ 1 (seg-sex, 11h-13h)"
      },
      "eligibilityRules": [
        {
          "field": "municipioIbge",
          "operator": "eq",
          "value": "1302603",
          "description": "Morar em Manaus"
        }
      ],
      "whereToApply": "Restaurantes Populares de Manaus",
      "documentsRequired": [],
      "howToApply": [
        "Vá a qualquer unidade Prato Cheio em Manaus",
        "Funcionamento: segunda a sexta, 11h às 13h",
        "Não precisa de cadastro"
      ],
      "sourceUrl": "https://www.seas.am.gov.br/prato-cheio-seas-indica-o-restaurante-popular-mais-proximo-do-usuario/",
      "lastUpdated": "2026-02-07",
      "status": "active",
      "icon": "🍽️",
      "category": "Alimentação",
      "verified": true,
      "templateGenerated": false
    },
    {
      "id": "am-manaus-transporte-social",
      "name": "Transporte Social",
      "shortDescription": "Meia-passagem ou gratuidade no transporte para baixa renda em Manaus. Verifique disponibilidade na prefeitura da sua cidade.",
      "scope": "municipal",
      "state": "AM",
      "municipalityIbge": "1302603",
      "estimatedValue": {
        "type": "monthly",
        "min": 0,
        "max": 0,
        "description": "Desconto de 50% a 100% na tarifa"
      },
      "eligibilityRules": [
        {
          "field": "municipioIbge",
          "operator": "eq",
          "value": "1302603",
          "description": "Morar em Manaus"
        },
        {
          "field": "cadastradoCadunico",
          "operator": "eq",
          "value": true,
          "description": "Estar no CadÚnico"
        },
        {
          "field": "rendaPerCapita",
          "operator": "lte",
          "value": 810.5,
          "description": "Renda por pessoa até meio salário mínimo"
        }
      ],
      "whereToApply": "Terminal de ônibus ou secretaria de transporte de Manaus",
      "documentsRequired": [
        "CPF",
        "RG",
        "NIS",
        "Comprovante de residência",
        "Foto 3x4"
      ],
      "howToApply": [
        "Procure o terminal de ônibus ou CRAS",
        "Apresente documentos",
        "Aguarde emissão do cartão"
      ],
      "sourceUrl": "https://www.manaus.am.gov.br",
      "lastUpdated": "2026-02-07",
      "status": "active",
      "icon": "🚌",
      "category": "Transporte",
      "verified": false,
      "templateGenerated": true
    },
    {
      "id": "am-manaus-iptu-social",
      "name": "IPTU Social",
      "shortDescription": "Isenção ou desconto no IPTU para famílias de baixa renda em Manaus. Verifique disponibilidade na prefeitura da sua cidade.",
      "scope": "municipal",
      "state": "AM",
      "municipalityIbge": "1302603",
      "estimatedValue": {
        "type": "annual",
        "min": 0,
        "max": 2000,
        "description": "Isenção de até 100% do IPTU"
      },
      "eligibilityRules": [
        {
          "field": "municipioIbge",
          "operator": "eq",
          "value": "1302603",
          "description": "Morar em Manaus"
        },
        {
          "field": "cadastradoCadunico",
          "operator": "eq",
          "value": true,
          "description": "Estar no CadÚnico"
        },
        {
          "field": "temCasaPropria",
          "operator": "eq",
          "value": true,
          "description": "Ter imóvel próprio"
        },
        {
          "field": "rendaPerCapita",
          "operator": "lte",
          "value": 810.5,
          "description": "Renda por pessoa até meio salário mínimo"
        }
      ],
      "whereToApply": "Secretaria da Fazenda de Manaus ou site da prefeitura",
      "documentsRequired": [
        "CPF",
        "RG",
        "Comprovante de residência",
        "Carnê do IPTU",
        "NIS"
      ],
      "howToApply": [
        "Acesse o site da prefeitura",
        "Solicite isenção no período de cadastro",
        "Aguarde análise"
      ],
      "sourceUrl": "https://www.manaus.am.gov.br",
      "lastUpdated": "2026-02-07",
      "status": "active",
      "icon": "🏠",
      "category": "Moradia",
      "verified": false,
      "templateGenerated": true
    },
    {
      "id": "am-manaus-habitacao-municipal",
      "name": "Programa Habitacional de Manaus",
      "shortDescription": "Moradia popular ou aluguel social para famílias em vulnerabilidade em Manaus. Verifique disponibilidade na prefeitura da sua cidade.",
      "scope": "municipal",
      "state": "AM",
      "municipalityIbge": "1302603",
      "estimatedValue": {
        "type": "monthly",
        "min": 300,
        "max": 600,
        "description": "Aluguel social de R$ 300 a R$ 600"
      },
      "eligibilityRules": [
        {
          "field": "municipioIbge",
          "operator": "eq",
          "value": "1302603",
          "description": "Morar em Manaus"
        },
        {
          "field": "cadastradoCadunico",
          "operator": "eq",
          "value": true,
          "description": "Estar no CadÚnico"
        },
        {
          "field": "temCasaPropria",
          "operator": "eq",
          "value": false,
          "description": "Não ter casa própria"
        },
        {
          "field": "rendaPerCapita",
          "operator": "lte",
          "value": 810.5,
          "description": "Renda por pessoa até meio salário mínimo"
        }
      ],
      "whereToApply": "CRAS ou Secretaria de Habitação de Manaus",
      "documentsRequired": [
        "CPF",
        "RG",
        "NIS",
        "Comprovante de residência",
        "Comprovante de renda"
      ],
      "howToApply": [
        "Procure o CRAS do seu bairro",
        "Solicite inclusão no programa habitacional",
        "Aguarde avaliação social"
      ],
      "sourceUrl": "https://www.manaus.am.gov.br",
      "lastUpdated": "2026-02-07",
      "status": "active",
      "icon": "🏡",
      "category": "Moradia",
      "verified": false,
      "templateGenerated": true
    }
  ]
}
